odoo8_addon_base_mixin_restrict_field_access-8.0.1.0.0.99.dev10-py3.8-nspkg.pth
odoo_addons/base_mixin_restrict_field_access/README.rst
odoo_addons/base_mixin_restrict_field_access/__init__.py
odoo_addons/base_mixin_restrict_field_access/__openerp__.py
odoo_addons/base_mixin_restrict_field_access/i18n/am.po
odoo_addons/base_mixin_restrict_field_access/i18n/ar.po
odoo_addons/base_mixin_restrict_field_access/i18n/base_mixin_restrict_field_access.pot
odoo_addons/base_mixin_restrict_field_access/i18n/bg.po
odoo_addons/base_mixin_restrict_field_access/i18n/bs.po
odoo_addons/base_mixin_restrict_field_access/i18n/ca.po
odoo_addons/base_mixin_restrict_field_access/i18n/ca_ES.po
odoo_addons/base_mixin_restrict_field_access/i18n/cs.po
odoo_addons/base_mixin_restrict_field_access/i18n/da.po
odoo_addons/base_mixin_restrict_field_access/i18n/de.po
odoo_addons/base_mixin_restrict_field_access/i18n/el_GR.po
odoo_addons/base_mixin_restrict_field_access/i18n/en_GB.po
odoo_addons/base_mixin_restrict_field_access/i18n/es.po
odoo_addons/base_mixin_restrict_field_access/i18n/es_AR.po
odoo_addons/base_mixin_restrict_field_access/i18n/es_CL.po
odoo_addons/base_mixin_restrict_field_access/i18n/es_CO.po
odoo_addons/base_mixin_restrict_field_access/i18n/es_CR.po
odoo_addons/base_mixin_restrict_field_access/i18n/es_DO.po
odoo_addons/base_mixin_restrict_field_access/i18n/es_EC.po
odoo_addons/base_mixin_restrict_field_access/i18n/es_ES.po
odoo_addons/base_mixin_restrict_field_access/i18n/es_MX.po
odoo_addons/base_mixin_restrict_field_access/i18n/es_PE.po
odoo_addons/base_mixin_restrict_field_access/i18n/es_PY.po
odoo_addons/base_mixin_restrict_field_access/i18n/es_VE.po
odoo_addons/base_mixin_restrict_field_access/i18n/et.po
odoo_addons/base_mixin_restrict_field_access/i18n/eu.po
odoo_addons/base_mixin_restrict_field_access/i18n/fa.po
odoo_addons/base_mixin_restrict_field_access/i18n/fi.po
odoo_addons/base_mixin_restrict_field_access/i18n/fr.po
odoo8_addon_base_mixin_restrict_field_access-8.0.1.0.0.99.dev10.dist-info/METADATA
odoo8_addon_base_mixin_restrict_field_access-8.0.1.0.0.99.dev10.dist-info/WHEEL
odoo8_addon_base_mixin_restrict_field_access-8.0.1.0.0.99.dev10.dist-info/namespace_packages.txt
odoo8_addon_base_mixin_restrict_field_access-8.0.1.0.0.99.dev10.dist-info/top_level.txt
odoo8_addon_base_mixin_restrict_field_access-8.0.1.0.0.99.dev10.dist-info/RECORD
